glacier_rsync/__init__.py
glacier_rsync/__main__.py
glacier_rsync/argparser.py
glacier_rsync/backup_util.py
glacier_rsync/file_cache.py
glacier_rsync/release.py
glacier_rsync-0.3.6.dist-info/COPYING
glacier_rsync-0.3.6.dist-info/METADATA
glacier_rsync-0.3.6.dist-info/WHEEL
glacier_rsync-0.3.6.dist-info/entry_points.txt
glacier_rsync-0.3.6.dist-info/top_level.txt
glacier_rsync-0.3.6.dist-info/RECORD
