Metadata-Version: 2.1
Name: glacier-rsync
Version: 0.3.6
Summary: Rsync like utility for backing up files/folders to AWS Glacier
Home-page: https://github.com/cagdasbas/glacier-rsync
Author: Cagdas Bas
Author-email: cagdasbs@gmail.com
License: UNKNOWN
Platform: UNKNOWN
Classifier: Development Status :: 5 - Production/Stable
Classifier: Intended Audience :: Developers
Classifier: Natural Language :: English
Classifier: License :: OSI Approved :: GNU General Public License v3 (GPLv3)
Classifier: Programming Language :: Python
Classifier: Programming Language :: Python :: 3
Classifier: Programming Language :: Python :: 3.8
Classifier: Programming Language :: Python :: 3.9
Requires-Python: >=3.8
Requires-Dist: boto3
Provides-Extra: compression
Requires-Dist: zstandard ; extra == 'compression'
